company_name_matcher/__init__.py
company_name_matcher/company_name_matcher.py
company_name_matcher/vector_store.py
company_name_matcher-0.1.2.dist-info/licenses/LICENSE
company_name_matcher-0.1.2.dist-info/METADATA
company_name_matcher-0.1.2.dist-info/WHEEL
company_name_matcher-0.1.2.dist-info/top_level.txt
company_name_matcher-0.1.2.dist-info/RECORD
