Metadata-Version: 2.4
Name: company_name_matcher
Version: 0.1.2
Summary: A library for matching and comparing company names using a fine-tuned sentence transformer model
Home-page: https://github.com/easonanalytica/company_name_matcher
Author: Eason Suen
Project-URL: Homepage, https://github.com/easonanalytica/company_name_matcher
Project-URL: Bug Tracker, https://github.com/easonanalytica/company_name_matcher/issues
Project-URL: Author, https://github.com/easonanalytica
Classifier: Intended Audience :: Developers
Classifier: License :: OSI Approved :: MIT License
Classifier: Operating System :: OS Independent
Classifier: Programming Language :: Python :: 3.9
Requires-Python: >=3.9
License-File: LICENSE
Requires-Dist: sentence-transformers>=3.3.1
Requires-Dist: numpy<2.0.0
Requires-Dist: scikit-learn>=1.6.0
Requires-Dist: h5py>=3.8.0
Requires-Dist: pandas>=2.0.0
Requires-Dist: pytest>=8.0.0
Dynamic: home-page
Dynamic: license-file
Dynamic: requires-python
